kwoq/__init__.py
kwoq/analysis.py
kwoq/api.py
kwoq-0.4.2.dist-info/METADATA
kwoq-0.4.2.dist-info/WHEEL
kwoq-0.4.2.dist-info/top_level.txt
kwoq-0.4.2.dist-info/RECORD
