Metadata-Version: 2.1
Name: kwoq
Version: 0.4.2
Summary: A simple data processing and visualization library
Author: Your Name
Author-email: your.email@example.com
Classifier: Programming Language :: Python :: 3
Classifier: License :: OSI Approved :: MIT License
Classifier: Operating System :: OS Independent
Requires-Python: >=3.7
Requires-Dist: numpy
Requires-Dist: pandas
Requires-Dist: matplotlib
Requires-Dist: scipy
Requires-Dist: statsmodels
Requires-Dist: seaborn
Requires-Dist: scikit-learn
Requires-Dist: requests
